miditeach/.gitattributes
miditeach/.gitignore
miditeach/__init__.py
miditeach/assets/images/select_off.png
miditeach/assets/images/select_on.png
miditeach/assets/sounds/correct.wav
miditeach/assets/sounds/wrong.wav
miditeach/miditeach.py
miditeach/read_stats.py
miditeach/stats/.gitignore
miditeach/views/__init__.py
miditeach/views/GameView.py
miditeach/views/LaunchView.py
miditeach/views/StopView.py
miditeach-0.7.dist-info/entry_points.txt
miditeach-0.7.dist-info/WHEEL
miditeach-0.7.dist-info/METADATA
miditeach-0.7.dist-info/RECORD
