Metadata-Version: 2.1
Name: miditeach
Version: 0.7
Summary: midiTeach is a music learning tool that can be used to practice your chords skills with a midi keyboard 🎹 !
Author: Alexis LOUIS
Author-email: alelouis.dev@gmail.com
Requires-Python: >=3.9,<4.0
Classifier: Programming Language :: Python :: 3
Classifier: Programming Language :: Python :: 3.9
Requires-Dist: arcade (>=2.5.7,<3.0.0)
Requires-Dist: mido (>=1.2.10,<2.0.0)
Requires-Dist: poetry-version (>=0.1.5,<0.2.0)
Requires-Dist: python-rtmidi (>=1.4.9,<2.0.0)
